.coveragerc
.eslintrc.json
.gitignore
.pre-commit-config.yaml
Gruntfile.js
LICENSE
Pipfile
README.rst
codecov.yml
package.json
pyproject.toml
setup.cfg
setup.py
tox.ini
.github/release-drafter.yml
.github/workflows/actions.yml
.github/workflows/release-drafter.yml
docs/Makefile
docs/api_reference.rst
docs/changelog.rst
docs/conf.py
docs/development.rst
docs/index.rst
docs/installing.rst
docs/make.bat
docs/user_guide.rst
src/.gitattributes
src/.gitignore
src/hhjin_pytest_html.egg-info/PKG-INFO
src/hhjin_pytest_html.egg-info/SOURCES.txt
src/hhjin_pytest_html.egg-info/dependency_links.txt
src/hhjin_pytest_html.egg-info/entry_points.txt
src/hhjin_pytest_html.egg-info/requires.txt
src/hhjin_pytest_html.egg-info/top_level.txt
src/layout/css/style.scss
src/pytest_html/__init__.py
src/pytest_html/__version.py
src/pytest_html/extras.py
src/pytest_html/hooks.py
src/pytest_html/html_report.py
src/pytest_html/outcome.py
src/pytest_html/plugin.py
src/pytest_html/result.py
src/pytest_html/util.py
src/pytest_html/resources/main.js
src/pytest_html/resources/style.css
testing/js_test_report.html
testing/test.js
testing/test_pytest_html.py